{"wiki": ["https://en.wikipedia.org/wiki/Gabon"], "capital": ["Libreville"], "continent": ["Africa"], "headState": ["Ali Bongo Ondimba"], "headGov": ["Emmanuel Issoze-Ngondet"], "pop": [{"year": "1963", "stats": "515762"}, {"year": "1975", "stats": "648174"}, {"year": "1978", "stats": "692535"}, {"year": "1966", "stats": "541895"}, {"year": "1968", "stats": "565080"}, {"year": "2007", "stats": "1447388"}, {"year": "1962", "stats": "509348"}, {"year": "1973", "stats": "623375"}, {"year": "2009", "stats": "1519155"}, {"year": "2006", "stats": "1412907"}, {"year": "1977", "stats": "676829"}, {"year": "2000", "stats": "1225527"}, {"year": "1983", "stats": "783527"}, {"year": "1998", "stats": "1166525"}, {"year": "1990", "stats": "946703"}, {"year": "1984", "stats": "804319"}, {"year": "2013", "stats": "1671711"}, {"year": "1974", "stats": "635318"}, {"year": "1964", "stats": "523236"}, {"year": "1969", "stats": "577241"}, {"year": "1996", "stats": "1108698"}, {"year": "1961", "stats": "503762"}, {"year": "2010", "stats": "1556222"}, {"year": "1989", "stats": "921314"}, {"year": "1967", "stats": "553098"}, {"year": "1992", "stats": "998823"}, {"year": "1980", "stats": "726454"}, {"year": "1985", "stats": "826025"}, {"year": "1995", "stats": "1080477"}, {"year": "1982", "stats": "763639"}, {"year": "1960", "stats": "498823"}, {"year": "1965", "stats": "531901"}, {"year": "1997", "stats": "1137412"}, {"year": "1976", "stats": "662036"}, {"year": "1970", "stats": "589165"}, {"year": "1971", "stats": "600692"}, {"year": "2003", "stats": "1315820"}, {"year": "1986", "stats": "848654"}, {"year": "1987", "stats": "872158"}, {"year": "1993", "stats": "1025559"}, {"year": "2011", "stats": "1594034"}, {"year": "2004", "stats": "1347125"}, {"year": "1999", "stats": "1195919"}, {"year": "2005", "stats": "1379465"}, {"year": "1988", "stats": "896429"}, {"year": "1991", "stats": "972539"}, {"year": "2008", "stats": "1482843"}, {"year": "1972", "stats": "611990"}, {"year": "1994", "stats": "1052772"}, {"year": "2012", "stats": "1632572"}, {"year": "1979", "stats": "709092"}, {"year": "2002", "stats": "1285318"}, {"year": "1981", "stats": "744624"}, {"year": "2001", "stats": "1255299"}], "hdi": [{"year": "1995", "stats": "0.633"}, {"year": "1990", "stats": "0.62"}, {"year": "2014", "stats": "0.684"}, {"year": "2010", "stats": "0.663"}, {"year": "2012", "stats": "0.673"}, {"year": "1980", "stats": "0.548"}, {"year": "2013", "stats": "0.679"}, {"year": "2000", "stats": "0.632"}, {"year": "2011", "stats": "0.668"}, {"year": "2005", "stats": "0.644"}, {"year": "1985", "stats": "0.596"}]}