{"capital": ["Dakar"], "continent": ["Africa"], "headState": ["Macky Sall"], "headGov": ["Mohamed Ben Abdallah Dionne"], "pop": [{"year": "2004", "stats": "10967568"}, {"year": "2000", "stats": "9861679"}, {"year": "2008", "stats": "12238791"}, {"year": "1962", "stats": "3356581"}, {"year": "1966", "stats": "3754429"}, {"year": "1961", "stats": "3265730"}, {"year": "1989", "stats": "7285204"}, {"year": "1995", "stats": "8711528"}, {"year": "2012", "stats": "13726021"}, {"year": "1974", "stats": "4765169"}, {"year": "1964", "stats": "3548083"}, {"year": "1987", "stats": "6846349"}, {"year": "1998", "stats": "9387783"}, {"year": "1967", "stats": "3862964"}, {"year": "2011", "stats": "13330737"}, {"year": "2003", "stats": "10673535"}, {"year": "1996", "stats": "8940298"}, {"year": "1970", "stats": "4218056"}, {"year": "1976", "stats": "5032394"}, {"year": "1978", "stats": "5289871"}, {"year": "1960", "stats": "3177737"}, {"year": "1979", "stats": "5424642"}, {"year": "1985", "stats": "6437891"}, {"year": "1969", "stats": "4094016"}, {"year": "1968", "stats": "3975826"}, {"year": "1983", "stats": "6062681"}, {"year": "1988", "stats": "7062329"}, {"year": "1972", "stats": "4485775"}, {"year": "1980", "stats": "5568908"}, {"year": "2013", "stats": "14133280"}, {"year": "2007", "stats": "11904974"}, {"year": "2001", "stats": "10119118"}, {"year": "1993", "stats": "8234586"}, {"year": "1992", "stats": "7990968"}, {"year": "1986", "stats": "6638009"}, {"year": "1981", "stats": "5723711"}, {"year": "1990", "stats": "7514110"}, {"year": "1975", "stats": "4901053"}, {"year": "1973", "stats": "4625876"}, {"year": "1971", "stats": "4348862"}, {"year": "1999", "stats": "9618564"}, {"year": "2002", "stats": "10390050"}, {"year": "1982", "stats": "5888343"}, {"year": "1991", "stats": "7749606"}, {"year": "2010", "stats": "12950564"}, {"year": "1977", "stats": "5160810"}, {"year": "1984", "stats": "6246065"}, {"year": "1997", "stats": "9164050"}, {"year": "1965", "stats": "3649456"}, {"year": "2006", "stats": "11582925"}, {"year": "2005", "stats": "11270826"}, {"year": "1963", "stats": "3450567"}, {"year": "2009", "stats": "12586827"}, {"year": "1994", "stats": "8475766"}], "hdi": [{"year": "2012", "stats": "0.461"}, {"year": "2013", "stats": "0.463"}, {"year": "2000", "stats": "0.38"}, {"year": "1990", "stats": "0.367"}, {"year": "2010", "stats": "0.456"}, {"year": "2014", "stats": "0.466"}, {"year": "1980", "stats": "0.325"}, {"year": "1985", "stats": "0.353"}, {"year": "2005", "stats": "0.422"}, {"year": "1995", "stats": "0.368"}, {"year": "2011", "stats": "0.458"}]}