{"wiki": ["https://en.wikipedia.org/wiki/Germany"], "capital": ["Berlin"], "continent": ["Europe"], "headState": ["Frank-Walter Steinmeier"], "headGov": ["Angela Merkel"], "pop": [{"year": "1986", "stats": "77780000"}, {"year": "2010", "stats": "81752000"}, {"year": "1988", "stats": "78390000"}, {"year": "1990", "stats": "79753000"}, {"year": "1966", "stats": "76864000"}, {"year": "2015", "stats": "81292400"}, {"year": "1970", "stats": "78069000"}, {"year": "1984", "stats": "77709000"}, {"year": "1956", "stats": "70943000"}, {"year": "1994", "stats": "81539000"}, {"year": "2012", "stats": "80500000"}, {"year": "2008", "stats": "82002000"}, {"year": "1976", "stats": "78209000"}, {"year": "1958", "stats": "72031000"}, {"year": "2006", "stats": "82315000"}, {"year": "1982", "stats": "78248000"}, {"year": "1992", "stats": "80975000"}, {"year": "1954", "stats": "70945000"}, {"year": "1996", "stats": "82012000"}, {"year": "1968", "stats": "77550000"}, {"year": "1978", "stats": "78073000"}, {"year": "2000", "stats": "82260000"}, {"year": "1974", "stats": "78882000"}, {"year": "2002", "stats": "82537000"}, {"year": "1980", "stats": "78397000"}, {"year": "2004", "stats": "82501000"}, {"year": "1960", "stats": "73147000"}, {"year": "1972", "stats": "78821000"}, {"year": "1964", "stats": "75591000"}, {"year": "2014", "stats": "81083600"}, {"year": "1998", "stats": "82037000"}, {"year": "1962", "stats": "74383000"}], "hdi": [{"year": "2000", "stats": "0.855"}, {"year": "1995", "stats": "0.83"}, {"year": "2010", "stats": "0.906"}, {"year": "2012", "stats": "0.915"}, {"year": "2014", "stats": "0.916"}, {"year": "2011", "stats": "0.911"}, {"year": "1990", "stats": "0.801"}, {"year": "2015", "stats": "0.926"}, {"year": "2013", "stats": "0.915"}, {"year": "2005", "stats": "0.887"}]}