{"capital": ["Rome"], "continent": ["Europe"], "headState": ["Sergio Mattarella"], "headGov": ["Paolo Gentiloni"], "pop": [{"year": "1984", "stats": "56576718"}, {"year": "1980", "stats": "56433883"}, {"year": "1960", "stats": "50199700"}, {"year": "1995", "stats": "56844303"}, {"year": "1977", "stats": "55955411"}, {"year": "2008", "stats": "58826731"}, {"year": "2001", "stats": "56974100"}, {"year": "2000", "stats": "56942108"}, {"year": "1967", "stats": "52900500"}, {"year": "1962", "stats": "50879450"}, {"year": "1993", "stats": "56831821"}, {"year": "1971", "stats": "54073490"}, {"year": "1994", "stats": "56843400"}, {"year": "2009", "stats": "59095365"}, {"year": "1986", "stats": "56596155"}, {"year": "1978", "stats": "56155143"}, {"year": "1976", "stats": "55718260"}, {"year": "1975", "stats": "55441001"}, {"year": "2002", "stats": "57059007"}, {"year": "1983", "stats": "56564074"}, {"year": "1968", "stats": "53235750"}, {"year": "1990", "stats": "56719240"}, {"year": "2005", "stats": "57969484"}, {"year": "1998", "stats": "56906744"}, {"year": "2006", "stats": "58143979"}, {"year": "1988", "stats": "56629288"}, {"year": "1965", "stats": "52112350"}, {"year": "1981", "stats": "56501675"}, {"year": "1969", "stats": "53537950"}, {"year": "1964", "stats": "51675350"}, {"year": "2003", "stats": "57313203"}, {"year": "1982", "stats": "56543548"}, {"year": "1999", "stats": "56916317"}, {"year": "1970", "stats": "53821850"}, {"year": "1966", "stats": "52519000"}, {"year": "2016", "stats": "60599936"}, {"year": "1991", "stats": "56758521"}, {"year": "1979", "stats": "56317749"}, {"year": "1985", "stats": "56593071"}, {"year": "2011", "stats": "59379449"}, {"year": "1997", "stats": "56890372"}, {"year": "2010", "stats": "59277417"}, {"year": "1996", "stats": "56860281"}, {"year": "1963", "stats": "51252000"}, {"year": "1989", "stats": "56671781"}, {"year": "1973", "stats": "54751406"}, {"year": "2007", "stats": "58438310"}, {"year": "2004", "stats": "57685327"}, {"year": "1974", "stats": "55110868"}, {"year": "1987", "stats": "56601931"}, {"year": "1961", "stats": "50536350"}, {"year": "2013", "stats": "60233948"}, {"year": "1992", "stats": "56797087"}, {"year": "1972", "stats": "54381345"}, {"year": "2012", "stats": "59539717"}], "hdi": [{"year": "1990", "stats": "0.766"}, {"year": "2011", "stats": "0.873"}, {"year": "1995", "stats": "0.799"}, {"year": "2014", "stats": "0.873"}, {"year": "2013", "stats": "0.873"}, {"year": "2000", "stats": "0.829"}, {"year": "2005", "stats": "0.856"}, {"year": "1980", "stats": "0.722"}, {"year": "2010", "stats": "0.869"}, {"year": "1985", "stats": "0.738"}, {"year": "2012", "stats": "0.872"}]}