{"capital": ["Beirut"], "continent": ["Asia"], "headState": ["Michel Aoun"], "headGov": ["Saad Hariri"], "pop": [{"year": "2009", "stats": "4246924"}, {"year": "1995", "stats": "3033406"}, {"year": "2000", "stats": "3235380"}, {"year": "1992", "stats": "2821868"}, {"year": "1963", "stats": "1984982"}, {"year": "1989", "stats": "2676615"}, {"year": "1983", "stats": "2651295"}, {"year": "1969", "stats": "2250609"}, {"year": "1971", "stats": "2353569"}, {"year": "1962", "stats": "1925276"}, {"year": "1961", "stats": "1864605"}, {"year": "1960", "stats": "1804927"}, {"year": "2011", "stats": "4382790"}, {"year": "1965", "stats": "2092354"}, {"year": "2008", "stats": "4186088"}, {"year": "1976", "stats": "2598362"}, {"year": "1967", "stats": "2174850"}, {"year": "1999", "stats": "3156706"}, {"year": "2004", "stats": "3853582"}, {"year": "1997", "stats": "3092718"}, {"year": "1998", "stats": "3114014"}, {"year": "1964", "stats": "2041212"}, {"year": "1985", "stats": "2676593"}, {"year": "1996", "stats": "3070984"}, {"year": "2010", "stats": "4341092"}, {"year": "2003", "stats": "3690110"}, {"year": "1988", "stats": "2668593"}, {"year": "2012", "stats": "4424888"}, {"year": "2013", "stats": "4467390"}, {"year": "1982", "stats": "2632281"}, {"year": "1994", "stats": "2974647"}, {"year": "1968", "stats": "2210965"}, {"year": "1973", "stats": "2480426"}, {"year": "1972", "stats": "2416743"}, {"year": "2007", "stats": "4139813"}, {"year": "1980", "stats": "2605294"}, {"year": "2002", "stats": "3515604"}, {"year": "1990", "stats": "2703019"}, {"year": "1984", "stats": "2667229"}, {"year": "1977", "stats": "2606224"}, {"year": "2006", "stats": "4079823"}, {"year": "1991", "stats": "2752473"}, {"year": "1974", "stats": "2535503"}, {"year": "1979", "stats": "2602573"}, {"year": "1966", "stats": "2136640"}, {"year": "1975", "stats": "2575693"}, {"year": "1981", "stats": "2615753"}, {"year": "1993", "stats": "2900862"}, {"year": "1986", "stats": "2677290"}, {"year": "2001", "stats": "3357600"}, {"year": "2005", "stats": "3986865"}, {"year": "1978", "stats": "2604875"}, {"year": "1970", "stats": "2297403"}, {"year": "1987", "stats": "2672182"}], "hdi": [{"year": "2005", "stats": "0.73"}, {"year": "2011", "stats": "0.761"}, {"year": "2012", "stats": "0.761"}, {"year": "2013", "stats": "0.768"}, {"year": "2010", "stats": "0.756"}, {"year": "2014", "stats": "0.769"}]}