{"capital": ["Mal\u00e9"], "continent": ["Asia"], "headState": ["Abdulla Yameen"], "headGov": ["Abdulla Yameen"], "pop": [{"year": "1988", "stats": "203072"}, {"year": "1977", "stats": "141736"}, {"year": "1999", "stats": "267456"}, {"year": "1990", "stats": "215859"}, {"year": "1987", "stats": "196513"}, {"year": "1993", "stats": "233611"}, {"year": "1997", "stats": "256347"}, {"year": "1983", "stats": "171015"}, {"year": "2013", "stats": "345023"}, {"year": "2008", "stats": "313843"}, {"year": "1982", "stats": "165053"}, {"year": "1961", "stats": "91319"}, {"year": "1978", "stats": "145563"}, {"year": "1970", "stats": "114150"}, {"year": "1994", "stats": "239291"}, {"year": "1967", "stats": "106072"}, {"year": "2006", "stats": "302825"}, {"year": "1966", "stats": "103759"}, {"year": "1991", "stats": "221963"}, {"year": "1984", "stats": "177213"}, {"year": "1962", "stats": "93806"}, {"year": "2000", "stats": "272745"}, {"year": "2003", "stats": "287594"}, {"year": "1971", "stats": "117664"}, {"year": "2001", "stats": "277825"}, {"year": "2011", "stats": "331964"}, {"year": "1968", "stats": "108458"}, {"year": "2002", "stats": "282743"}, {"year": "1976", "stats": "137965"}, {"year": "1979", "stats": "149699"}, {"year": "1963", "stats": "96358"}, {"year": "1975", "stats": "134077"}, {"year": "2010", "stats": "325694"}, {"year": "2014", "stats": "401000"}, {"year": "1973", "stats": "125780"}, {"year": "1980", "stats": "154316"}, {"year": "1998", "stats": "261973"}, {"year": "1981", "stats": "159459"}, {"year": "1969", "stats": "111106"}, {"year": "1986", "stats": "189974"}, {"year": "1960", "stats": "88960"}, {"year": "2005", "stats": "297576"}, {"year": "1996", "stats": "250659"}, {"year": "2007", "stats": "308239"}, {"year": "1974", "stats": "129993"}, {"year": "2004", "stats": "292505"}, {"year": "1985", "stats": "183538"}, {"year": "2012", "stats": "338442"}, {"year": "1972", "stats": "121593"}, {"year": "1964", "stats": "98899"}, {"year": "1992", "stats": "227863"}, {"year": "2009", "stats": "319660"}, {"year": "1989", "stats": "209545"}, {"year": "1965", "stats": "101381"}, {"year": "1995", "stats": "244965"}], "hdi": [{"year": "2014", "stats": "0.706"}, {"year": "2013", "stats": "0.703"}, {"year": "2005", "stats": "0.638"}, {"year": "2012", "stats": "0.695"}, {"year": "2011", "stats": "0.69"}, {"year": "2010", "stats": "0.683"}, {"year": "2000", "stats": "0.603"}]}